commitor/__init__.py
commitor/cli.py
commitor/prompt.py
commitor-0.1.1.dist-info/LICENSE
commitor-0.1.1.dist-info/METADATA
commitor-0.1.1.dist-info/WHEEL
commitor-0.1.1.dist-info/entry_points.txt
commitor-0.1.1.dist-info/RECORD
